USAggregate/__init__.py
USAggregate/usaggregate.py
USAggregate/data/tracts.csv
USAggregate/data/zipcodes.csv
USAggregate-1.1.12.dist-info/LICENSE
USAggregate-1.1.12.dist-info/METADATA
USAggregate-1.1.12.dist-info/WHEEL
USAggregate-1.1.12.dist-info/top_level.txt
USAggregate-1.1.12.dist-info/RECORD
